{"textures":{"0":"modelengine:entity/skull_kid"},"elements":[{"from":[4.0,9.142858,5.714286],"to":[12.0,9.142858,13.714286],"rotation":{"angle":0.0,"axis":"y","origin":[6.857143,8.0,9.714286]},"faces":{"east":{"uv":[0.0,1.75,1.75,2.125],"rotation":0,"texture":"#missing","tintindex":0},"south":{"uv":[5.25,1.75,7.0,2.125],"rotation":0,"texture":"#missing","tintindex":0},"north":{"uv":[1.75,1.75,3.5,2.125],"rotation":0,"texture":"#missing","tintindex":0},"west":{"uv":[3.5,1.75,5.25,2.125],"rotation":0,"texture":"#missing","tintindex":0},"up":{"uv":[3.5,1.75,1.75,0.0],"rotation":0,"texture":"#0","tintindex":0},"down":{"uv":[3.5,0.0,1.75,1.75],"rotation":0,"texture":"#0","tintindex":0}}},{"from":[4.0,7.428571,13.714286],"to":[12.0,9.142858,13.714286],"rotation":{"angle":0.0,"axis":"y","origin":[6.857143,8.0,9.714286]},"faces":{"east":{"uv":[0.0,1.75,1.75,2.125],"rotation":0,"texture":"#missing","tintindex":0},"south":{"uv":[5.25,1.75,7.0,2.125],"rotation":0,"texture":"#0","tintindex":0},"north":{"uv":[7.0,1.75,5.25,2.125],"rotation":0,"texture":"#0","tintindex":0},"west":{"uv":[3.5,1.75,5.25,2.125],"rotation":0,"texture":"#missing","tintindex":0},"up":{"uv":[3.5,1.75,1.75,0.0],"rotation":0,"texture":"#missing","tintindex":0},"down":{"uv":[5.25,0.0,3.5,1.75],"rotation":0,"texture":"#missing","tintindex":0}}},{"from":[4.0,7.428571,5.714286],"to":[12.0,9.142858,5.714286],"rotation":{"angle":0.0,"axis":"y","origin":[6.857143,8.0,9.714286]},"faces":{"east":{"uv":[0.0,1.75,1.75,2.125],"rotation":0,"texture":"#missing","tintindex":0},"south":{"uv":[3.5,1.75,1.75,2.125],"rotation":0,"texture":"#0","tintindex":0},"north":{"uv":[1.75,1.75,3.5,2.125],"rotation":0,"texture":"#0","tintindex":0},"west":{"uv":[3.5,1.75,5.25,2.125],"rotation":0,"texture":"#missing","tintindex":0},"up":{"uv":[3.5,1.75,1.75,0.0],"rotation":0,"texture":"#missing","tintindex":0},"down":{"uv":[5.25,0.0,3.5,1.75],"rotation":0,"texture":"#missing","tintindex":0}}},{"from":[4.0,7.428571,5.714286],"to":[4.0,9.142858,13.714286],"rotation":{"angle":0.0,"axis":"y","origin":[6.857143,8.0,9.714286]},"faces":{"east":{"uv":[5.25,1.75,3.5,2.125],"rotation":0,"texture":"#0","tintindex":0},"south":{"uv":[5.25,1.75,7.0,2.125],"rotation":0,"texture":"#missing","tintindex":0},"north":{"uv":[1.75,1.75,3.5,2.125],"rotation":0,"texture":"#missing","tintindex":0},"west":{"uv":[3.5,1.75,5.25,2.125],"rotation":0,"texture":"#0","tintindex":0},"up":{"uv":[3.5,1.75,1.75,0.0],"rotation":0,"texture":"#missing","tintindex":0},"down":{"uv":[5.25,0.0,3.5,1.75],"rotation":0,"texture":"#missing","tintindex":0}}},{"from":[12.0,7.428571,5.714286],"to":[12.0,9.142858,13.714286],"rotation":{"angle":0.0,"axis":"y","origin":[6.857143,8.0,9.714286]},"faces":{"east":{"uv":[0.0,1.75,1.75,2.125],"rotation":0,"texture":"#0","tintindex":0},"south":{"uv":[5.25,1.75,7.0,2.125],"rotation":0,"texture":"#missing","tintindex":0},"north":{"uv":[1.75,1.75,3.5,2.125],"rotation":0,"texture":"#missing","tintindex":0},"west":{"uv":[1.75,1.75,0.0,2.125],"rotation":0,"texture":"#0","tintindex":0},"up":{"uv":[3.5,1.75,1.75,0.0],"rotation":0,"texture":"#missing","tintindex":0},"down":{"uv":[5.25,0.0,3.5,1.75],"rotation":0,"texture":"#missing","tintindex":0}}},{"from":[5.142857,9.142858,7.428571],"to":[10.857143,12.0,12.0],"rotation":{"angle":0.0,"axis":"y","origin":[6.857143,9.142858,9.714286]},"faces":{"east":{"uv":[0.0,5.125,1.0,5.75],"rotation":0,"texture":"#0","tintindex":0},"south":{"uv":[3.25,5.125,4.5,5.75],"rotation":0,"texture":"#0","tintindex":0},"north":{"uv":[1.0,5.125,2.25,5.75],"rotation":0,"texture":"#0","tintindex":0},"west":{"uv":[2.25,5.125,3.25,5.75],"rotation":0,"texture":"#0","tintindex":0},"up":{"uv":[2.25,5.125,1.0,4.125],"rotation":0,"texture":"#0","tintindex":0},"down":{"uv":[3.5,4.125,2.25,5.125],"rotation":0,"texture":"#missing","tintindex":0}}},{"from":[5.714286,14.285715,9.714286],"to":[5.714286,18.857143,14.285715],"rotation":{"angle":0.0,"axis":"y","origin":[8.0,14.285715,9.714286]},"faces":{"east":{"uv":[3.0,3.125,2.0,4.125],"rotation":0,"texture":"#0","tintindex":0},"south":{"uv":[3.0,3.125,4.0,4.125],"rotation":0,"texture":"#missing","tintindex":0},"north":{"uv":[1.0,3.125,2.0,4.125],"rotation":0,"texture":"#missing","tintindex":0},"west":{"uv":[2.0,3.125,3.0,4.125],"rotation":0,"texture":"#0","tintindex":0},"up":{"uv":[2.0,3.125,1.0,2.125],"rotation":0,"texture":"#missing","tintindex":0},"down":{"uv":[3.0,2.125,2.0,3.125],"rotation":0,"texture":"#missing","tintindex":0}}},{"from":[10.285714,14.285715,9.714286],"to":[10.285714,18.857143,14.285715],"rotation":{"angle":0.0,"axis":"y","origin":[8.0,14.285715,9.714286]},"faces":{"east":{"uv":[0.0,3.125,1.0,4.125],"rotation":0,"texture":"#0","tintindex":0},"south":{"uv":[3.0,3.125,4.0,4.125],"rotation":0,"texture":"#missing","tintindex":0},"north":{"uv":[1.0,3.125,2.0,4.125],"rotation":0,"texture":"#missing","tintindex":0},"west":{"uv":[1.0,3.125,0.0,4.125],"rotation":0,"texture":"#0","tintindex":0},"up":{"uv":[2.0,3.125,1.0,2.125],"rotation":0,"texture":"#missing","tintindex":0},"down":{"uv":[3.0,2.125,2.0,3.125],"rotation":0,"texture":"#missing","tintindex":0}}},{"from":[5.714286,14.285715,9.714286],"to":[10.285714,18.857143,9.714286],"rotation":{"angle":0.0,"axis":"y","origin":[8.0,14.285715,9.714286]},"faces":{"east":{"uv":[0.0,3.125,1.0,4.125],"rotation":0,"texture":"#missing","tintindex":0},"south":{"uv":[2.0,3.125,1.0,4.125],"rotation":0,"texture":"#0","tintindex":0},"north":{"uv":[1.0,3.125,2.0,4.125],"rotation":0,"texture":"#0","tintindex":0},"west":{"uv":[2.0,3.125,3.0,4.125],"rotation":0,"texture":"#missing","tintindex":0},"up":{"uv":[2.0,3.125,1.0,2.125],"rotation":0,"texture":"#missing","tintindex":0},"down":{"uv":[3.0,2.125,2.0,3.125],"rotation":0,"texture":"#missing","tintindex":0}}},{"from":[5.714286,14.285715,9.714286],"to":[10.285714,14.285715,14.285715],"rotation":{"angle":0.0,"axis":"y","origin":[8.0,14.285715,9.714286]},"faces":{"east":{"uv":[0.0,3.125,1.0,4.125],"rotation":0,"texture":"#missing","tintindex":0},"south":{"uv":[3.0,3.125,4.0,4.125],"rotation":0,"texture":"#missing","tintindex":0},"north":{"uv":[1.0,3.125,2.0,4.125],"rotation":0,"texture":"#missing","tintindex":0},"west":{"uv":[2.0,3.125,3.0,4.125],"rotation":0,"texture":"#missing","tintindex":0},"up":{"uv":[3.0,3.125,2.0,2.125],"rotation":0,"texture":"#0","tintindex":0},"down":{"uv":[3.0,2.125,2.0,3.125],"rotation":0,"texture":"#0","tintindex":0}}},{"from":[6.857143,13.714286,9.142858],"to":[9.142858,14.857143,10.285714],"rotation":{"angle":0.0,"axis":"y","origin":[6.857143,12.0,9.714286]},"faces":{"east":{"uv":[4.5,5.5,4.75,5.75],"rotation":0,"texture":"#0","tintindex":0},"south":{"uv":[5.5,5.5,6.0,5.75],"rotation":0,"texture":"#0","tintindex":0},"north":{"uv":[4.75,5.5,5.25,5.75],"rotation":0,"texture":"#0","tintindex":0},"west":{"uv":[5.25,5.5,5.5,5.75],"rotation":0,"texture":"#0","tintindex":0},"up":{"uv":[5.25,5.5,4.75,5.25],"rotation":0,"texture":"#0","tintindex":0},"down":{"uv":[5.75,5.25,5.25,5.5],"rotation":0,"texture":"#missing","tintindex":0}}},{"from":[6.285714,12.0,8.571428],"to":[9.714286,13.714286,10.857143],"rotation":{"angle":0.0,"axis":"y","origin":[5.714286,9.142858,9.714286]},"faces":{"east":{"uv":[0.0,6.25,0.5,6.625],"rotation":0,"texture":"#0","tintindex":0},"south":{"uv":[1.75,6.25,2.5,6.625],"rotation":0,"texture":"#0","tintindex":0},"north":{"uv":[0.5,6.25,1.25,6.625],"rotation":0,"texture":"#0","tintindex":0},"west":{"uv":[1.25,6.25,1.75,6.625],"rotation":0,"texture":"#0","tintindex":0},"up":{"uv":[1.25,6.25,0.5,5.75],"rotation":0,"texture":"#0","tintindex":0},"down":{"uv":[2.0,5.75,1.25,6.25],"rotation":0,"texture":"#missing","tintindex":0}}}],"display":{"head":{"translation":[0.0,-6.4,0.0],"scale":[4.0,4.0,4.0]}}}