{"textures":{"0":"modelengine:entity/texture"},"elements":[{"from":[6.285714,8.0,6.857143],"to":[9.714286,13.142858,9.142858],"rotation":{"angle":0.0,"axis":"y","origin":[8.0,1.7142854,8.571428]},"faces":{"east":{"uv":[5.25,5.25,5.75,6.375],"rotation":0,"texture":"#0","tintindex":0},"south":{"uv":[5.75,5.25,6.5,6.375],"rotation":0,"texture":"#0","tintindex":0},"north":{"uv":[5.75,5.25,6.5,6.375],"rotation":0,"texture":"#0","tintindex":0},"west":{"uv":[6.5,5.25,7.0,6.375],"rotation":0,"texture":"#0","tintindex":0},"up":{"uv":[6.5,5.25,5.75,4.75],"rotation":0,"texture":"#0","tintindex":0},"down":{"uv":[7.25,4.75,6.5,5.25],"rotation":0,"texture":"#0","tintindex":0}}},{"from":[5.428571,7.714286,5.714286],"to":[10.571428,14.571428,6.857143],"rotation":{"angle":0.0,"axis":"y","origin":[8.0,8.571428,8.571428]},"faces":{"east":{"uv":[1.5,0.25,1.75,1.75],"rotation":0,"texture":"#0","tintindex":0},"south":{"uv":[3.125,0.25,4.25,1.75],"rotation":0,"texture":"#0","tintindex":0},"north":{"uv":[1.75,0.25,2.875,1.75],"rotation":0,"texture":"#0","tintindex":0},"west":{"uv":[2.875,0.25,3.125,1.75],"rotation":0,"texture":"#0","tintindex":0},"up":{"uv":[2.875,0.25,1.75,0.0],"rotation":0,"texture":"#0","tintindex":0},"down":{"uv":[4.0,0.0,2.875,0.25],"rotation":0,"texture":"#0","tintindex":0}}},{"from":[4.285714,8.571428,6.142857],"to":[6.0,10.285714,6.714286],"rotation":{"angle":45.0,"axis":"z","origin":[5.428571,9.714286,6.857143]},"faces":{"east":{"uv":[1.25,0.875,1.375,1.25],"rotation":0,"texture":"#0","tintindex":0},"south":{"uv":[1.5,0.5,1.125,0.875],"rotation":0,"texture":"#0","tintindex":0},"north":{"uv":[1.125,0.5,0.75,0.875],"rotation":0,"texture":"#0","tintindex":0},"west":{"uv":[1.25,0.875,1.375,1.25],"rotation":0,"texture":"#0","tintindex":0},"up":{"uv":[1.125,0.5,1.5,0.625],"rotation":0,"texture":"#0","tintindex":0},"down":{"uv":[1.125,0.5,1.5,0.625],"rotation":0,"texture":"#0","tintindex":0}}},{"from":[10.0,8.571428,6.142857],"to":[11.714286,10.285714,6.714286],"rotation":{"angle":-45.0,"axis":"z","origin":[10.571428,9.714286,6.857143]},"faces":{"east":{"uv":[1.25,0.875,1.375,1.25],"rotation":0,"texture":"#0","tintindex":0},"south":{"uv":[1.125,0.5,1.5,0.875],"rotation":0,"texture":"#0","tintindex":0},"north":{"uv":[0.75,0.5,1.125,0.875],"rotation":0,"texture":"#0","tintindex":0},"west":{"uv":[1.25,0.875,1.375,1.25],"rotation":0,"texture":"#0","tintindex":0},"up":{"uv":[1.5,0.5,1.125,0.625],"rotation":0,"texture":"#0","tintindex":0},"down":{"uv":[1.5,0.5,1.125,0.625],"rotation":0,"texture":"#0","tintindex":0}}},{"from":[7.142857,6.857143,6.285714],"to":[8.857143,8.571428,6.857143],"rotation":{"angle":-45.0,"axis":"z","origin":[8.0,7.714286,6.5714283]},"faces":{"east":{"uv":[0.625,0.125,0.75,0.5],"rotation":0,"texture":"#0","tintindex":0},"south":{"uv":[1.125,0.125,1.5,0.5],"rotation":0,"texture":"#0","tintindex":0},"north":{"uv":[0.75,0.125,1.125,0.5],"rotation":0,"texture":"#0","tintindex":0},"west":{"uv":[0.625,0.125,0.75,0.5],"rotation":0,"texture":"#0","tintindex":0},"up":{"uv":[1.0,0.0,0.625,0.125],"rotation":0,"texture":"#0","tintindex":0},"down":{"uv":[1.0,0.0,0.625,0.125],"rotation":0,"texture":"#0","tintindex":0}}}],"display":{"head":{"translation":[0.0,-6.4,0.0],"scale":[4.0,4.0,4.0]}}}